{"note":"Don't delete this file! It's used internally to help with page regeneration.","name":"DionaeaFR","tagline":"Dionaea Front Web","google":"","body":"DionaeaFR\r\n=========\r\n\r\nFront Web to Dionaea log analysis.\r\n\r\nHome Dionaea: http://dionaea.carnivore.it/\r\n\r\n[*] Technologies:\r\n\r\n  - Python 2.7.3\r\n  - Django 1.4\r\n  - Jquery 1.7.2\r\n  - Bootstrap Framework 2.1.1\r\n  - jVectorMap 1.0\r\n  - Kendo-UI v2011.3.1129\r\n  - SQLite3\r\n\r\n[*] Requeriments:\r\n\r\n\tpip install Django\r\n\tpip install pygeoip\r\n\tpip install django-pagination\r\n\tpip install django-tables2\r\n\t\r\n\tdjango-tables2-simplefilter:\r\n\t\thttps://github.com/benjiec/django-tables2-simplefilter\r\n\r\n[*] Install\r\n\r\n  Copy /opt/dionaea/var/dionaea/logsql.sqlite to DionaeaFR root directory\r\n\r\n  Download GeoIP.dat and GeoLiteCity.dat from https://www.maxmind.com/en/home and copy in DionaeaFR/static\r\n\r\n  Change STATICFILES_DIRS in DionaeaFR/Dionaea/settings.py to absolute paths of DionaeaFR/static\r\n\r\n  Change TEMPLATE_DIRS in DionaeaFR/Dionaea/settings.py to absolute paths of DionaeaFR/Templates\r\n\r\n  python manage.py collectstatic\r\n\r\n  python manage.py runserver\r\n\r\n  Access to http://localhost:8000 in browser.\r\n\r\n[*] Changelog\r\n\r\n  - Add transport, type and protocol filters in connections table.\r\n\r\nSuggestions?\r\n\r\nDesigned by @rubenespadas"}